build/lib/infinity/__init__.py
build/lib/infinity/common.py
build/lib/infinity/connection_pool.py
build/lib/infinity/db.py
build/lib/infinity/errors.py
build/lib/infinity/index.py
build/lib/infinity/infinity.py
build/lib/infinity/rag_tokenizer.py
build/lib/infinity/table.py
build/lib/infinity/utils.py
build/lib/infinity/remote_thrift/__init__.py
build/lib/infinity/remote_thrift/client.py
build/lib/infinity/remote_thrift/db.py
build/lib/infinity/remote_thrift/infinity.py
build/lib/infinity/remote_thrift/query_builder.py
build/lib/infinity/remote_thrift/table.py
build/lib/infinity/remote_thrift/types.py
build/lib/infinity/remote_thrift/utils.py
build/lib/infinity/remote_thrift/infinity_thrift_rpc/InfinityService.py
build/lib/infinity/remote_thrift/infinity_thrift_rpc/__init__.py
build/lib/infinity/remote_thrift/infinity_thrift_rpc/constants.py
build/lib/infinity/remote_thrift/infinity_thrift_rpc/ttypes.py
infinity/__init__.py
infinity/common.py
infinity/connection_pool.py
infinity/db.py
infinity/errors.py
infinity/http_utils.py
infinity/index.py
infinity/infinity.py
infinity/infinity_http.py
infinity/rag_tokenizer.py
infinity/table.py
infinity/utils.py
infinity/remote_thrift/__init__.py
infinity/remote_thrift/client.py
infinity/remote_thrift/db.py
infinity/remote_thrift/infinity.py
infinity/remote_thrift/query_builder.py
infinity/remote_thrift/table.py
infinity/remote_thrift/types.py
infinity/remote_thrift/utils.py
infinity/remote_thrift/infinity_thrift_rpc/InfinityService.py
infinity/remote_thrift/infinity_thrift_rpc/__init__.py
infinity/remote_thrift/infinity_thrift_rpc/constants.py
infinity/remote_thrift/infinity_thrift_rpc/ttypes.py
infinity_sdk-0.6.14.dist-info/licenses/LICENSE
infinity_sdk-0.6.14.dist-info/METADATA
infinity_sdk-0.6.14.dist-info/WHEEL
infinity_sdk-0.6.14.dist-info/top_level.txt
infinity_sdk-0.6.14.dist-info/RECORD
