Metadata-Version: 2.4
Name: infinity-sdk
Version: 0.6.14
Summary: infinity
Requires-Python: <3.15,>=3.11
License-File: LICENSE
Requires-Dist: sqlglot[rs]>=27.10.0
Requires-Dist: pydantic<3.0.0,>=2.9.0
Requires-Dist: thrift<1.0.0,>=0.20.0
Requires-Dist: setuptools<81.0.0,>=78.1.1
Requires-Dist: pandas<3.0.0,>=2.2.0
Requires-Dist: numpy<2.0.0,>=1.26.0
Requires-Dist: pyarrow<23.0.0,>=17.0.0
Requires-Dist: polars-lts-cpu<2.0.0,>=1.9.0
Requires-Dist: requests<3.0.0,>=2.32.3
Requires-Dist: readerwriterlock<2.0.0,>=1.0.0
Requires-Dist: datrie<0.9.0,>=0.8.3
Requires-Dist: hanziconv<0.4.0,>=0.3.0
Requires-Dist: nltk<4.0.0,>=3.9.1
Provides-Extra: test
Requires-Dist: pytest<10.0.0,>=8.3.0; extra == "test"
Requires-Dist: tomli<3.0.0,>=2.0.2; extra == "test"
Requires-Dist: psutil<8.0.0,>=6.0.0; extra == "test"
Requires-Dist: docker<8.0.0,>=7.1.0; extra == "test"
Requires-Dist: tomli-w<2.0.0,>=1.1.0; extra == "test"
Requires-Dist: timeout-decorator<0.6.0,>=0.5.0; extra == "test"
Provides-Extra: benchmark
Requires-Dist: elasticsearch<10.0.0,>=8.13.0; extra == "benchmark"
Requires-Dist: h5py<4.0.0,>=3.11.0; extra == "benchmark"
Requires-Dist: qdrant_client<2.0.0,>=1.9.0; extra == "benchmark"
Dynamic: license-file
